{
  "id": "img_1768608338343",
  "sessionId": "iFWhANwetmAYa1yqsisx",
  "version": 1,
  "createdAt": "2026-01-17 00:05:38",
  "archivedAt": "2026-02-04 20:14:23",
  "imageUrl": "https://zosky.github.io/zoskyCube-archive/pixelPower/2026/01/img_1768608338343.png",
  "sentenceHighlightUrl": "https://zosky.github.io/zoskyCube-archive/pixelPower/2026/01/img_1768608338343_sentence.png",
  "audioUrl": "https://zosky.github.io/zoskyCube-archive/pixelPower/2026/01/img_1768608338343_narration.mp3",
  "youtubeId": "SSJoq5i1Tzk",
  "youtubeUrl": "https://youtu.be/SSJoq5i1Tzk",
  "originalImageUrl": "https://storage.googleapis.com/zoskycube-bossbattle.firebasestorage.app/generated_images/1768608338343_In_a_particular_international_market_where_the_vib.png",
  "originalAudioUrl": null,
  "generatedSentence": "In a particular international market, where the vibrant photosynthesis of exotic plants created a delicate, verdant visibility, an undergraduate, whose identity was usually masked by a nonphysical aura of quiet study, felt a sudden, surprised jolt of joy as this generation's strange events began to galvanize his evening, becoming truly abhorrent when a jinxed old jalopy, its vulcanized tires squealing, knocked over a display with aggressive force, sparking immediate irritation, only for three clumsy knuckleheads to tumble from the wreckage, their sequential system of operations clearly compromised, one attempting to kneel and retrieve a single gigabyte flash drive from his rather exposed underwear, while another, almost abducted by gravity, tried to mount a wobbly unicycle – a versatile but utterly useless escape vehicle – and the third, adding to the bizarre narration of the scene, fumbled with a mysterious medication bottle, perhaps a potent narcotic, just snatched from a directory listing delicious street food vendors, making the whole chaotic spectacle, a peculiar intersection of urban psychophysics and absurd reality, leave the student yearning for the simple peace of breaking a merrythought with a friend.",
  "panelSentences": null,
  "rawPanelSentences": null,
  "imagePrompt": null,
  "wordCount": 36,
  "totalPoints": 6258,
  "contributorCount": 13,
  "playerContributions": {
    "johnnymnemonics": {
      "displayName": "JohnnyMnemonics",
      "totalPoints": 767,
      "wordCount": 5,
      "words": [
        "generation",
        "abducted",
        "undergraduate",
        "delicate",
        "medication"
      ],
      "avatar": "https://static-cdn.jtvnw.net/user-default-pictures-uv/dbdc9198-def8-11e9-8681-784f43822e80-profile_image-300x300.png",
      "percentage": 12
    },
    "johnic1983": {
      "displayName": "johnic1983",
      "totalPoints": 338,
      "wordCount": 2,
      "words": [
        "galvanize",
        "particular"
      ],
      "avatar": "https://static-cdn.jtvnw.net/user-default-pictures-uv/ebb84563-db81-4b9c-8940-64ed33ccfc7b-profile_image-300x300.png",
      "percentage": 5
    },
    "madagascaradam": {
      "displayName": "madagascaradam",
      "totalPoints": 1111,
      "wordCount": 6,
      "words": [
        "gigabyte",
        "underwear",
        "jalopy",
        "identity",
        "photosynthesis",
        "directory"
      ],
      "avatar": "https://static-cdn.jtvnw.net/jtv_user_pictures/2b2e43c0-0da8-437c-8f34-407dd2ab4e6b-profile_image-300x300.png",
      "percentage": 18
    },
    "valase": {
      "displayName": "Valase",
      "totalPoints": 325,
      "wordCount": 2,
      "words": [
        "vulcanized",
        "sequential"
      ],
      "avatar": "https://static-cdn.jtvnw.net/jtv_user_pictures/4e37be0c-a737-4129-a5ba-1a55e0dfa935-profile_image-300x300.png",
      "percentage": 5
    },
    "thanossoul": {
      "displayName": "thanossoul",
      "totalPoints": 572,
      "wordCount": 4,
      "words": [
        "versatile",
        "joy",
        "irritation",
        "kneel"
      ],
      "avatar": "https://static-cdn.jtvnw.net/user-default-pictures-uv/de130ab0-def7-11e9-b668-784f43822e80-profile_image-300x300.png",
      "percentage": 9
    },
    "calypso_ba": {
      "displayName": "calypso_ba",
      "totalPoints": 234,
      "wordCount": 1,
      "words": [
        "visibility"
      ],
      "avatar": "https://static-cdn.jtvnw.net/user-default-pictures-uv/ead5c8b2-a4c9-4724-b1dd-9f00b46cbd3d-profile_image-300x300.png",
      "percentage": 4
    },
    "yurigiu": {
      "displayName": "yurigiu",
      "totalPoints": 533,
      "wordCount": 3,
      "words": [
        "abhorrent",
        "surprised",
        "unicycle"
      ],
      "avatar": "https://static-cdn.jtvnw.net/user-default-pictures-uv/de130ab0-def7-11e9-b668-784f43822e80-profile_image-300x300.png",
      "percentage": 9
    },
    "alfims": {
      "displayName": "alfiMS",
      "totalPoints": 195,
      "wordCount": 1,
      "words": [
        "aggressive"
      ],
      "avatar": "https://static-cdn.jtvnw.net/jtv_user_pictures/alfims-profile_image-045aea46e6e58b61-300x300.png",
      "percentage": 3
    },
    "smogracing": {
      "displayName": "SMOGRacing",
      "totalPoints": 227,
      "wordCount": 2,
      "words": [
        "system",
        "international"
      ],
      "avatar": "https://static-cdn.jtvnw.net/jtv_user_pictures/42c09a3b-f0d8-409a-95c3-047ee151f21d-profile_image-300x300.png",
      "percentage": 4
    },
    "player0451": {
      "displayName": "player0451",
      "totalPoints": 169,
      "wordCount": 1,
      "words": [
        "jinxed"
      ],
      "avatar": "https://static-cdn.jtvnw.net/user-default-pictures-uv/ce57700a-def9-11e9-842d-784f43822e80-profile_image-300x300.png",
      "percentage": 3
    },
    "somemarblesfriday": {
      "displayName": "someMarblesFriday",
      "totalPoints": 968,
      "wordCount": 4,
      "words": [
        "knuckleheads",
        "psychophysics",
        "merrythought",
        "nonphysical"
      ],
      "avatar": "https://static-cdn.jtvnw.net/jtv_user_pictures/3091cf17-f7a1-4bbc-8c53-38c0aa1d2c31-profile_image-300x300.png",
      "percentage": 15
    },
    "avin_novor": {
      "displayName": "Avin_Novor",
      "totalPoints": 546,
      "wordCount": 3,
      "words": [
        "knocked",
        "delicious",
        "narcotic"
      ],
      "avatar": "https://static-cdn.jtvnw.net/jtv_user_pictures/ffd2fb8a-65ae-4742-bb59-05cb462e28f9-profile_image-300x300.png",
      "percentage": 9
    },
    "snoopys030": {
      "displayName": "snoopys030",
      "totalPoints": 273,
      "wordCount": 2,
      "words": [
        "market",
        "narration"
      ],
      "avatar": "https://static-cdn.jtvnw.net/jtv_user_pictures/snoopys030-profile_image-1704f6f890f25fa7-300x300.jpeg",
      "percentage": 4
    }
  },
  "words": [],
  "roundCount": {
    "startTime": 1768607624160,
    "letter": "N",
    "number": 12
  },
  "wordsPerRound": null,
  "letterQueue": [
    "N",
    "F",
    "H",
    "L",
    "E",
    "Y",
    "O",
    "T",
    "R",
    "W",
    "C",
    "B",
    "G",
    "V",
    "A",
    "S",
    "U",
    "J",
    "I",
    "K",
    "P",
    "D",
    "M"
  ],
  "videoTitle": null,
  "videoDescription": null,
  "videoDuration": null,
  "model": "imagen-nano",
  "estimatedCost": 0.11,
  "_generatedAt": "2026-02-06T18:41:40.729Z",
  "_generator": "generateArchiveMetadata.js"
}